sneakpeak/__init__.py
sneakpeak-0.1.1.dist-info/WHEEL
sneakpeak-0.1.1.dist-info/METADATA
sneakpeak-0.1.1.dist-info/RECORD
