Metadata-Version: 2.1
Name: sneakpeak
Version: 0.1.1
Summary: A python module to generate data for link preview.
Home-page: https://github.com/codingcoffee/sneakpeak
License: MIT
Keywords: open-graph-protocol,ogp,twitter,twitter-cards,python,schema,link-preview
Author: Ameya Shenoy
Author-email: shenoy.ameya@gmail.com
Maintainer: Ameya Shenoy
Maintainer-email: shenoy.ameya@gmail.com
Requires-Python: >=3.10,<4.0
Classifier: Development Status :: 4 - Beta
Classifier: Intended Audience :: Developers
Classifier: License :: OSI Approved :: MIT License
Classifier: Operating System :: POSIX :: Linux
Classifier: Operating System :: Unix
Classifier: Programming Language :: Python :: 3
Classifier: Programming Language :: Python :: 3.0
Classifier: Programming Language :: Python :: 3.1
Classifier: Programming Language :: Python :: 3.10
Classifier: Programming Language :: Python :: 3.11
Classifier: Programming Language :: Python :: 3.12
Classifier: Programming Language :: Python :: 3.2
Classifier: Programming Language :: Python :: 3.3
Classifier: Programming Language :: Python :: 3.4
Classifier: Programming Language :: Python :: 3.5
Classifier: Programming Language :: Python :: 3.6
Classifier: Programming Language :: Python :: 3.7
Classifier: Programming Language :: Python :: 3.8
Classifier: Programming Language :: Python :: 3.9
Classifier: Topic :: Software Development :: Build Tools
Classifier: Topic :: Software Development :: Libraries
Classifier: Topic :: Software Development :: Libraries :: Python Modules
Classifier: Topic :: Text Processing :: Markup :: HTML
Classifier: Topic :: Utilities
Project-URL: Documentation, https://github.com/codingcoffee/sneakpeak
Project-URL: Repository, https://github.com/codingcoffee/sneakpeak
